consultapmuxm/__init__.py
consultapmuxm/consultapmuxm.py
consultapmuxm-1.0.7.dist-info/METADATA
consultapmuxm-1.0.7.dist-info/WHEEL
consultapmuxm-1.0.7.dist-info/top_level.txt
consultapmuxm-1.0.7.dist-info/RECORD
